queryrewrite/__init__.py
queryrewrite/requirements.txt
queryrewrite/llm/__init__.py
queryrewrite/llm/base.py
queryrewrite/llm/ollama.py
queryrewrite/rewriting/__init__.py
queryrewrite/rewriting/base.py
queryrewrite/rewriting/glossary_rewriter.py
queryrewrite/rewriting/llm_rewriter.py
queryrewrite/rewriting/synonym_rewriter.py
queryrewrite/utils/__init__.py
queryrewrite/utils/data_models.py
queryrewrite/utils/super_float.py
queryrewrite/utils/super_json.py
queryrewrite/utils/super_list.py
queryrewrite/validation/__init__.py
queryrewrite/validation/base.py
queryrewrite/validation/metrics.py
queryrewrite/validation/validators.py
queryrewrite-0.1.0.dist-info/licenses/LICENSE
queryrewrite-0.1.0.dist-info/METADATA
queryrewrite-0.1.0.dist-info/WHEEL
queryrewrite-0.1.0.dist-info/top_level.txt
queryrewrite-0.1.0.dist-info/RECORD
