Metadata-Version: 2.4
Name: queryrewrite
Version: 0.1.0
Summary: A Python project for query rewriting using LLMs and other methods.
Author-email: CrissChan <your@email.com>
License: MIT
Classifier: Development Status :: 3 - Alpha
Classifier: Intended Audience :: Developers
Classifier: License :: OSI Approved :: MIT License
Classifier: Programming Language :: Python :: 3
Classifier: Programming Language :: Python :: 3.8
Classifier: Programming Language :: Python :: 3.9
Classifier: Programming Language :: Python :: 3.10
Classifier: Programming Language :: Python :: 3.11
Classifier: Topic :: Software Development :: Libraries :: Python Modules
Classifier: Topic :: Scientific/Engineering :: Artificial Intelligence
Requires-Python: >=3.8
License-File: LICENSE
Requires-Dist: langchain
Requires-Dist: langchain-ollama
Requires-Dist: ollama
Requires-Dist: jieba
Requires-Dist: rouge-score
Requires-Dist: nltk
Requires-Dist: sacrebleu
Requires-Dist: pytest
Requires-Dist: pytest-mock
Dynamic: license-file
